[
    {
        "id": "22901",
        "train": "1269",
        "station": "223",
        "seq": "9",
        "arrival": "02:20:00",
        "departure": "02:30:00",
        "distance": "489"
    },
    {
        "id": "22902",
        "train": "1269",
        "station": "25",
        "seq": "10",
        "arrival": "04:30:00",
        "departure": "04:40:00",
        "distance": "623"
    },
    {
        "id": "22903",
        "train": "1269",
        "station": "1596",
        "seq": "11",
        "arrival": "05:25:00",
        "departure": "05:27:00",
        "distance": "684"
    },
    {
        "id": "22904",
        "train": "1269",
        "station": "1489",
        "seq": "12",
        "arrival": "05:50:00",
        "departure": "05:52:00",
        "distance": "714"
    },
    {
        "id": "22905",
        "train": "1269",
        "station": "1699",
        "seq": "13",
        "arrival": "06:08:00",
        "departure": "06:10:00",
        "distance": "738"
    },
    {
        "id": "22906",
        "train": "1269",
        "station": "1488",
        "seq": "14",
        "arrival": "06:40:00",
        "departure": "06:43:00",
        "distance": "774"
    },
    {
        "id": "22907",
        "train": "1269",
        "station": "1700",
        "seq": "15",
        "arrival": "07:08:00",
        "departure": "07:10:00",
        "distance": "801"
    },
    {
        "id": "22908",
        "train": "1269",
        "station": "286",
        "seq": "16",
        "arrival": "08:23:00",
        "departure": "08:25:00",
        "distance": "848"
    },
    {
        "id": "22909",
        "train": "1269",
        "station": "1725",
        "seq": "17",
        "arrival": "08:43:00",
        "departure": "08:45:00",
        "distance": "869"
    },
    {
        "id": "22910",
        "train": "1269",
        "station": "1487",
        "seq": "18",
        "arrival": "09:06:00",
        "departure": "09:08:00",
        "distance": "899"
    },
    {
        "id": "22911",
        "train": "1269",
        "station": "1486",
        "seq": "19",
        "arrival": "09:24:00",
        "departure": "09:26:00",
        "distance": "916"
    },
    {
        "id": "22912",
        "train": "1269",
        "station": "272",
        "seq": "20",
        "arrival": "10:10:00",
        "departure": "10:10:00",
        "distance": "930"
    },
    {
        "id": "22913",
        "train": "1270",
        "station": "272",
        "seq": "1",
        "arrival": "15:20:00",
        "departure": "15:20:00",
        "distance": "0"
    },
    {
        "id": "22914",
        "train": "1270",
        "station": "1486",
        "seq": "2",
        "arrival": "15:48:00",
        "departure": "15:50:00",
        "distance": "14"
    },
    {
        "id": "22915",
        "train": "1270",
        "station": "1487",
        "seq": "3",
        "arrival": "16:06:00",
        "departure": "16:08:00",
        "distance": "31"
    },
    {
        "id": "22916",
        "train": "1270",
        "station": "1725",
        "seq": "4",
        "arrival": "16:29:00",
        "departure": "16:31:00",
        "distance": "61"
    },
    {
        "id": "22917",
        "train": "1270",
        "station": "286",
        "seq": "5",
        "arrival": "17:05:00",
        "departure": "17:07:00",
        "distance": "82"
    },
    {
        "id": "22918",
        "train": "1270",
        "station": "1700",
        "seq": "6",
        "arrival": "17:42:00",
        "departure": "17:43:00",
        "distance": "129"
    },
    {
        "id": "22919",
        "train": "1270",
        "station": "1488",
        "seq": "7",
        "arrival": "18:03:00",
        "departure": "18:06:00",
        "distance": "156"
    },
    {
        "id": "22920",
        "train": "1270",
        "station": "1699",
        "seq": "8",
        "arrival": "18:31:00",
        "departure": "18:32:00",
        "distance": "192"
    },
    {
        "id": "22921",
        "train": "1270",
        "station": "1489",
        "seq": "9",
        "arrival": "18:51:00",
        "departure": "18:53:00",
        "distance": "217"
    },
    {
        "id": "22922",
        "train": "1270",
        "station": "1596",
        "seq": "10",
        "arrival": "19:13:00",
        "departure": "19:15:00",
        "distance": "246"
    },
    {
        "id": "22923",
        "train": "1270",
        "station": "25",
        "seq": "11",
        "arrival": "20:25:00",
        "departure": "20:35:00",
        "distance": "307"
    },
    {
        "id": "22924",
        "train": "1270",
        "station": "223",
        "seq": "12",
        "arrival": "22:40:00",
        "departure": "22:50:00",
        "distance": "441"
    },
    {
        "id": "22925",
        "train": "1270",
        "station": "1781",
        "seq": "13",
        "arrival": "23:41:00",
        "departure": "23:43:00",
        "distance": "494"
    },
    {
        "id": "22926",
        "train": "1270",
        "station": "995",
        "seq": "14",
        "arrival": "01:44:00",
        "departure": "01:46:00",
        "distance": "648"
    },
    {
        "id": "22927",
        "train": "1270",
        "station": "994",
        "seq": "15",
        "arrival": "03:40:00",
        "departure": "03:50:00",
        "distance": "747"
    },
    {
        "id": "22928",
        "train": "1270",
        "station": "993",
        "seq": "16",
        "arrival": "05:00:00",
        "departure": "05:02:00",
        "distance": "799"
    },
    {
        "id": "22929",
        "train": "1270",
        "station": "1981",
        "seq": "17",
        "arrival": "05:34:00",
        "departure": "05:36:00",
        "distance": "843"
    },
    {
        "id": "22930",
        "train": "1270",
        "station": "992",
        "seq": "18",
        "arrival": "05:58:00",
        "departure": "06:00:00",
        "distance": "864"
    },
    {
        "id": "22931",
        "train": "1270",
        "station": "1281",
        "seq": "19",
        "arrival": "06:49:00",
        "departure": "06:51:00",
        "distance": "926"
    },
    {
        "id": "22932",
        "train": "1270",
        "station": "231",
        "seq": "20",
        "arrival": "07:40:00",
        "departure": "07:40:00",
        "distance": "933"
    },
    {
        "id": "22933",
        "train": "1271",
        "station": "231",
        "seq": "1",
        "arrival": "00:00:00",
        "departure": "17:05:00",
        "distance": "0"
    },
    {
        "id": "22934",
        "train": "1271",
        "station": "232",
        "seq": "2",
        "arrival": "17:45:00",
        "departure": "17:46:00",
        "distance": "45"
    },
    {
        "id": "22935",
        "train": "1271",
        "station": "233",
        "seq": "3",
        "arrival": "18:04:00",
        "departure": "18:06:00",
        "distance": "63"
    },
    {
        "id": "22936",
        "train": "1271",
        "station": "111",
        "seq": "4",
        "arrival": "19:20:00",
        "departure": "19:35:00",
        "distance": "99"
    },
    {
        "id": "22937",
        "train": "1271",
        "station": "1298",
        "seq": "5",
        "arrival": "20:45:00",
        "departure": "20:47:00",
        "distance": "172"
    },
    {
        "id": "22938",
        "train": "1271",
        "station": "1299",
        "seq": "6",
        "arrival": "21:50:00",
        "departure": "21:52:00",
        "distance": "246"
    },
    {
        "id": "22939",
        "train": "1271",
        "station": "112",
        "seq": "7",
        "arrival": "23:35:00",
        "departure": "23:40:00",
        "distance": "361"
    },
    {
        "id": "22940",
        "train": "1271",
        "station": "274",
        "seq": "8",
        "arrival": "02:55:00",
        "departure": "03:00:00",
        "distance": "627"
    },
    {
        "id": "22941",
        "train": "1271",
        "station": "94",
        "seq": "9",
        "arrival": "08:00:00",
        "departure": "08:02:00",
        "distance": "947"
    },
    {
        "id": "22942",
        "train": "1271",
        "station": "275",
        "seq": "10",
        "arrival": "10:40:00",
        "departure": "00:00:00",
        "distance": "1075"
    },
    {
        "id": "22943",
        "train": "1272",
        "station": "275",
        "seq": "1",
        "arrival": "13:55:00",
        "departure": "13:55:00",
        "distance": "0"
    },
    {
        "id": "22944",
        "train": "1272",
        "station": "94",
        "seq": "2",
        "arrival": "16:03:00",
        "departure": "16:05:00",
        "distance": "130"
    },
    {
        "id": "22945",
        "train": "1272",
        "station": "274",
        "seq": "3",
        "arrival": "19:45:00",
        "departure": "19:50:00",
        "distance": "450"
    },
    {
        "id": "22946",
        "train": "1272",
        "station": "112",
        "seq": "4",
        "arrival": "23:45:00",
        "departure": "23:50:00",
        "distance": "715"
    },
    {
        "id": "22947",
        "train": "1272",
        "station": "1299",
        "seq": "5",
        "arrival": "01:13:00",
        "departure": "01:15:00",
        "distance": "830"
    },
    {
        "id": "22948",
        "train": "1272",
        "station": "1298",
        "seq": "6",
        "arrival": "02:53:00",
        "departure": "02:55:00",
        "distance": "905"
    },
    {
        "id": "22949",
        "train": "1272",
        "station": "111",
        "seq": "7",
        "arrival": "04:05:00",
        "departure": "04:20:00",
        "distance": "978"
    },
    {
        "id": "22950",
        "train": "1272",
        "station": "233",
        "seq": "8",
        "arrival": "04:55:00",
        "departure": "04:57:00",
        "distance": "1013"
    },
    {
        "id": "22951",
        "train": "1272",
        "station": "232",
        "seq": "9",
        "arrival": "05:12:00",
        "departure": "05:14:00",
        "distance": "1032"
    },
    {
        "id": "22952",
        "train": "1272",
        "station": "231",
        "seq": "10",
        "arrival": "06:10:00",
        "departure": "06:10:00",
        "distance": "1077"
    },
    {
        "id": "22953",
        "train": "1273",
        "station": "1345",
        "seq": "1",
        "arrival": "12:25:00",
        "departure": "12:25:00",
        "distance": "0"
    },
    {
        "id": "22954",
        "train": "1273",
        "station": "1346",
        "seq": "2",
        "arrival": "13:09:00",
        "departure": "13:11:00",
        "distance": "38"
    },
    {
        "id": "22955",
        "train": "1273",
        "station": "113",
        "seq": "3",
        "arrival": "13:50:00",
        "departure": "14:10:00",
        "distance": "78"
    },
    {
        "id": "22956",
        "train": "1273",
        "station": "1300",
        "seq": "4",
        "arrival": "14:42:00",
        "departure": "14:43:00",
        "distance": "119"
    },
    {
        "id": "22957",
        "train": "1273",
        "station": "1353",
        "seq": "5",
        "arrival": "14:58:00",
        "departure": "15:00:00",
        "distance": "138"
    },
    {
        "id": "22958",
        "train": "1273",
        "station": "1470",
        "seq": "6",
        "arrival": "15:23:00",
        "departure": "15:25:00",
        "distance": "168"
    },
    {
        "id": "22959",
        "train": "1273",
        "station": "1352",
        "seq": "7",
        "arrival": "15:38:00",
        "departure": "15:40:00",
        "distance": "181"
    },
    {
        "id": "22960",
        "train": "1273",
        "station": "1471",
        "seq": "8",
        "arrival": "15:53:00",
        "departure": "15:54:00",
        "distance": "194"
    },
    {
        "id": "22961",
        "train": "1273",
        "station": "1351",
        "seq": "9",
        "arrival": "16:17:00",
        "departure": "16:19:00",
        "distance": "223"
    },
    {
        "id": "22962",
        "train": "1273",
        "station": "114",
        "seq": "10",
        "arrival": "16:41:00",
        "departure": "16:43:00",
        "distance": "251"
    },
    {
        "id": "22963",
        "train": "1273",
        "station": "96",
        "seq": "11",
        "arrival": "17:20:00",
        "departure": "17:35:00",
        "distance": "262"
    },
    {
        "id": "22964",
        "train": "1273",
        "station": "146",
        "seq": "12",
        "arrival": "18:14:00",
        "departure": "18:16:00",
        "distance": "315"
    },
    {
        "id": "22965",
        "train": "1273",
        "station": "1072",
        "seq": "13",
        "arrival": "18:45:00",
        "departure": "18:47:00",
        "distance": "354"
    },
    {
        "id": "22966",
        "train": "1273",
        "station": "145",
        "seq": "14",
        "arrival": "19:35:00",
        "departure": "19:40:00",
        "distance": "400"
    },
    {
        "id": "22967",
        "train": "1273",
        "station": "120",
        "seq": "15",
        "arrival": "20:23:00",
        "departure": "20:25:00",
        "distance": "463"
    },
    {
        "id": "22968",
        "train": "1273",
        "station": "1073",
        "seq": "16",
        "arrival": "21:08:00",
        "departure": "21:10:00",
        "distance": "527"
    },
    {
        "id": "22969",
        "train": "1273",
        "station": "40",
        "seq": "17",
        "arrival": "21:55:00",
        "departure": "22:05:00",
        "distance": "551"
    },
    {
        "id": "22970",
        "train": "1273",
        "station": "1199",
        "seq": "18",
        "arrival": "22:25:00",
        "departure": "22:27:00",
        "distance": "576"
    },
    {
        "id": "22971",
        "train": "1273",
        "station": "1201",
        "seq": "19",
        "arrival": "22:49:00",
        "departure": "22:51:00",
        "distance": "606"
    },
    {
        "id": "22972",
        "train": "1273",
        "station": "95",
        "seq": "20",
        "arrival": "23:28:00",
        "departure": "23:33:00",
        "distance": "648"
    },
    {
        "id": "22973",
        "train": "1273",
        "station": "1202",
        "seq": "21",
        "arrival": "23:54:00",
        "departure": "23:56:00",
        "distance": "687"
    },
    {
        "id": "22974",
        "train": "1273",
        "station": "1203",
        "seq": "22",
        "arrival": "00:35:00",
        "departure": "00:37:00",
        "distance": "703"
    },
    {
        "id": "22975",
        "train": "1273",
        "station": "35",
        "seq": "23",
        "arrival": "01:20:00",
        "departure": "01:25:00",
        "distance": "755"
    },
    {
        "id": "22976",
        "train": "1273",
        "station": "1204",
        "seq": "24",
        "arrival": "01:33:00",
        "departure": "01:35:00",
        "distance": "759"
    },
    {
        "id": "22977",
        "train": "1273",
        "station": "94",
        "seq": "25",
        "arrival": "02:13:00",
        "departure": "02:16:00",
        "distance": "809"
    },
    {
        "id": "22978",
        "train": "1273",
        "station": "1205",
        "seq": "26",
        "arrival": "02:44:00",
        "departure": "02:46:00",
        "distance": "849"
    },
    {
        "id": "22979",
        "train": "1273",
        "station": "1206",
        "seq": "27",
        "arrival": "03:38:00",
        "departure": "03:40:00",
        "distance": "890"
    },
    {
        "id": "22980",
        "train": "1273",
        "station": "1207",
        "seq": "28",
        "arrival": "03:58:00",
        "departure": "04:00:00",
        "distance": "911"
    },
    {
        "id": "22981",
        "train": "1273",
        "station": "1016",
        "seq": "29",
        "arrival": "04:11:00",
        "departure": "04:13:00",
        "distance": "919"
    },
    {
        "id": "22982",
        "train": "1273",
        "station": "275",
        "seq": "30",
        "arrival": "04:36:00",
        "departure": "04:38:00",
        "distance": "937"
    },
    {
        "id": "22983",
        "train": "1273",
        "station": "121",
        "seq": "31",
        "arrival": "05:00:00",
        "departure": "05:20:00",
        "distance": "944"
    },
    {
        "id": "22984",
        "train": "1273",
        "station": "58",
        "seq": "32",
        "arrival": "06:13:00",
        "departure": "06:15:00",
        "distance": "988"
    },
    {
        "id": "22985",
        "train": "1273",
        "station": "59",
        "seq": "33",
        "arrival": "06:48:00",
        "departure": "06:50:00",
        "distance": "1033"
    },
    {
        "id": "22986",
        "train": "1273",
        "station": "60",
        "seq": "34",
        "arrival": "07:13:00",
        "departure": "07:15:00",
        "distance": "1068"
    },
    {
        "id": "22987",
        "train": "1273",
        "station": "61",
        "seq": "35",
        "arrival": "07:41:00",
        "departure": "07:43:00",
        "distance": "1101"
    },
    {
        "id": "22988",
        "train": "1273",
        "station": "62",
        "seq": "36",
        "arrival": "08:55:00",
        "departure": "09:05:00",
        "distance": "1142"
    },
    {
        "id": "22989",
        "train": "1273",
        "station": "1255",
        "seq": "37",
        "arrival": "09:47:00",
        "departure": "09:49:00",
        "distance": "1196"
    },
    {
        "id": "22990",
        "train": "1273",
        "station": "1256",
        "seq": "38",
        "arrival": "10:02:00",
        "departure": "10:04:00",
        "distance": "1213"
    },
    {
        "id": "22991",
        "train": "1273",
        "station": "122",
        "seq": "39",
        "arrival": "10:55:00",
        "departure": "11:15:00",
        "distance": "1256"
    },
    {
        "id": "22992",
        "train": "1273",
        "station": "268",
        "seq": "40",
        "arrival": "12:00:00",
        "departure": "12:05:00",
        "distance": "1308"
    },
    {
        "id": "22993",
        "train": "1273",
        "station": "1258",
        "seq": "41",
        "arrival": "12:50:00",
        "departure": "12:52:00",
        "distance": "1366"
    },
    {
        "id": "22994",
        "train": "1273",
        "station": "1259",
        "seq": "42",
        "arrival": "13:08:00",
        "departure": "13:10:00",
        "distance": "1381"
    },
    {
        "id": "22995",
        "train": "1273",
        "station": "269",
        "seq": "43",
        "arrival": "13:55:00",
        "departure": "14:00:00",
        "distance": "1421"
    },
    {
        "id": "22996",
        "train": "1273",
        "station": "377",
        "seq": "44",
        "arrival": "14:33:00",
        "departure": "14:35:00",
        "distance": "1444"
    },
    {
        "id": "22997",
        "train": "1273",
        "station": "270",
        "seq": "45",
        "arrival": "16:10:00",
        "departure": "16:20:00",
        "distance": "1520"
    },
    {
        "id": "22998",
        "train": "1273",
        "station": "1982",
        "seq": "46",
        "arrival": "16:35:00",
        "departure": "16:37:00",
        "distance": "1531"
    },
    {
        "id": "22999",
        "train": "1273",
        "station": "1983",
        "seq": "47",
        "arrival": "16:49:00",
        "departure": "16:51:00",
        "distance": "1542"
    },
    {
        "id": "23000",
        "train": "1273",
        "station": "1984",
        "seq": "48",
        "arrival": "17:03:00",
        "departure": "17:05:00",
        "distance": "1552"
    }
]